{
  "contract": "계약(서)",
  "submission": "제출, 제기",
  "shortage": "부족",
  "capacity": "(생산) 능력, 수용력",
  "distribution": "유통, 배부, 분포",
  "facility": "시설, 기관",
  "reputation": "평판",
  "assignment": "과제, 업무, 임무",
  "entrance": "입구",
  "shareholder": "주주",
  "delight": "기쁨, 즐거움",
  "request": "요청",
  "claim": "청구, 신청",
  "remain": "계속 ~이다, 남아 있다",
  "address": "(문제 등을) 다루다",
  "accelerate": "가속화하다",
  "commence": "시작하다",
  "join": "가입하다, 합류하다",
  "maximize": "극대화하다",
  "memorize": "암기하다",
  "prove": "증명하다, 입증하다",
  "strive": "노력하다, 분투하다",
  "grant": "승인하다, 수여하다",
  "recycle": "재활용하다, 재사용하다",
  "acquire": "획득하다, 얻다",
  "alert": "알리다, 경고하다",
  "redeem": "(상품권 등을) 현금으로 바꾸다",
  "endure": "견디다",
  "ship": "운송하다",
  "guarantee": "보장하다",
  "visualize": "예상하다, 시각화하다",
  "purchase": "구매하다",
  "renew": "갱신하다",
  "deliver": "배달하다",
  "expire": "만료되다",
  "undergo": "받다, 겪다",
  "consent": "동의하다, 허락하다",
  "assure": "보장하다, 안심시키다",
  "increase": "증가시키다, 인상하다",
  "indicate": "명시하다, 나타내다",
  "rate": "평가하다",
  "reclaim": "되찾다",
  "tolerate": "용인하다, 견디다",
  "divide": "나누다",
  "affect": "~에 영향을 미치다",
  "depart": "출발하다, 떠나다",
  "eliminate": "제거하다, 없애다",
  "reject": "거절하다, 거부하다",
  "attract": "끌어모으다, 유인하다",
  "classify": "분류하다, 구분하다",
  "withdraw": "(계좌에서 돈을) 인출하다",
  "donate": "기부하다",
  "support": "지지하다, 후원하다",
  "exceed": "초과하다, 넘다",
  "finalize": "완성하다, 마무리하다",
  "present": "수여하다, 주다",
  "disrupt": "지장을 주다, 방해하다",
  "argue": "주장하다, 언쟁하다",
  "assess": "평가하다",
  "divert": "다른 곳으로 돌리다, 우회시키다",
  "establish": "설립하다, 수립하다",
  "suspect": "의심하다",
  "rephrase": "바꾸어 말하다",
  "expand": "확장시키다",
  "enclose": "동봉하다",
  "verify": "확인하다, 증명하다",
  "omit": "생략하다, 누락하다",
  "capture": "획득하다, 포착하다",
  "cite": "인용하다",
  "appoint": "임명하다, 지정하다",
  "demonstrate": "시연하다, 설명하다",
  "cancel": "취소하다",
  "suspend": "중단하다, 정지하다",
  "diverse": "다양한, 여러 가지의",
  "excessive": "매우 많은, 과도한",
  "prestigious": "일류의, 명망 있는",
  "comprehensive": "종합적인, 포괄적인",
  "resistant": "~에 강한, 저항하는",
  "elaborate": "복잡한, 공을 들인",
  "current": "현재의",
  "revised": "수정된, 변경된",
  "affordable": "가격이 알맞은, 저렴한",
  "practical": "실용적인",
  "time-consuming": "시간이 걸리는",
  "relevant": "관련 있는, 적절한",
  "adequate": "충분한, 적절한",
  "minor": "가벼운, 중요치 않은",
  "productive": "생산적인",
  "flexible": "유동적인",
  "loyal": "충성스러운, 충실한",
  "fertile": "비옥한, 기름진",
  "vacant": "빈, 사람이 없는",
  "hollow": "속이 빈",
  "renowned": "유명한, 명성 있는",
  "valid": "유효한, 타당한",
  "frustrating": "불만스러운, 좌절스러운",
  "sole": "유일한, 혼자의",
  "proficient": "능숙한, 숙달한",
  "lively": "활기찬, 강경한",
  "economic": "경제적인, 경제성이 있는",
  "relaxing": "나른한",
  "profitable": "수익성 있는",
  "wasteful": "낭비적인, 소모적인",
  "alternative": "다른, 대안적인",
  "domestic": "국내의",
  "respectful": "존중하는, 공손한",
  "sizable": "상당한",
  "disappointing": "실망스러운",
  "conventional": "관습적인, 전통적인",
  "fair": "공정한, 공평한",
  "distinctive": "독특한",
  "original": "원래의, 최초의",
  "introductory": "입문의, 서론의",
  "reliable": "신뢰할 수 있는, 믿을 만한",
  "potential": "잠재적인, 가능성 있는",
  "efficient": "효율적인, 능률적인",
  "unanticipated": "예상 밖의",
  "prominent": "유명한, 탁월한",
  "knowledgeable": "아는 것이 많은, 총명한",
  "appropriate": "적절한, 적당한",
  "combustible": "가연성의",
  "equivalent": "동등한, 상당하는",
  "residential": "주거의, 거주의",
  "deliberate": "신중한, 의도적인",
  "frequent": "빈번한, 잦은",
  "standard": "표준의, 보통의",
  "insistent": "주장하는",
  "commercial": "상업의",
  "legitimate": "합법적인, 합리적인",
  "punctual": "시간을 엄수하는",
  "decisive": "결단력 있는, 결정적인",
  "cautious": "주의하는, 조심스러운",
  "delicate": "다루기 어려운, 섬세한, 까다로운",
  "access": "접근하다, 들어가다",
  "ensure": "반드시 ~하게 하다, 보장하다",
  "feature": "포함하다, 특징으로 삼다",
  "contend": "주장하다, 다투다",
  "determine": "알아내다, 결정하다",
  "award": "주다, 수여하다",
  "decline": "거부하다, 감소하다",
  "discuss": "논의하다",
  "review": "검토하다, 확인하다",
  "serve": "봉사하다, (음식 등을) 제공하다",
  "obtain": "입수하다, 획득하다",
  "minimize": "최소화하다",
  "merge": "합병하다, 통합하다",
  "duplicate": "복사하다, 복제하다",
  "pursue": "추구하다, 계속하다",
  "host": "주최하다",
  "gather": "수집하다, 모으다",
  "reset": "재설정하다",
  "inform": "알려주다",
  "announce": "발표하다, 공지하다",
  "previous": "이전의",
  "sensitive": "민감한",
  "substantial": "상당한, 튼튼한",
  "convincing": "설득력 있는, 확실한",
  "diligent": "성실한, 부지런한",
  "promising": "유망한, 전망이 밝은",
  "comfortable": "안락한, 편안한",
  "available": "구할 수 있는",
  "impressive": "인상적인",
  "direct": "직접적인",
  "credible": "신뢰할 수 있는",
  "lengthy": "장황한, 지루한",
  "preferred": "선호하는, 선호되는",
  "rigorous": "엄격한, 철저한",
  "mundane": "일상적인, 따분한",
  "overpriced": "너무 비싼",
  "conclusive": "결정적인",
  "imaginary": "가상의",
  "recent": "최근의",
  "late": "늦은",
  "accurately": "정확히, 정밀하게",
  "routinely": "일상적으로, 언제나",
  "markedly": "현저하게, 두드러지게",
  "superbly": "훌륭하게,  최상으로",
  "closely": "면밀히, 유심히",
  "intentionally": "의도적으로, 고의로",
  "merely": "단지, 그저",
  "acceptably": "만족스럽게",
  "probably": "아마도",
  "gradually": "서서히, 차츰",
  "namely": "다시 말해, 즉",
  "primarily": "주로",
  "aboard": "탑승하여",
  "occasionally": "종종, 가끔",
  "completely": "완전히, 전적으로",
  "understandably": "당연히",
  "apparently": "보아하니, 분명히",
  "necessarily": "반드시 ~은 아니다",
  "immediately": "즉시",
  "briefly": "간략하게, 잠시",
  "exclusively": "오직 ~만, 독점적으로",
  "promptly": "지체 없이, 신속히",
  "relatively": "비교적, 상대적으로",
  "periodically": "정기적으로",
  "elsewhere": "다른 곳에서",
  "barely": "거의 ~하지 않은, 가까스로",
  "justly": "정당하게, 바르게",
  "inseparably": "밀접하게",
  "largely": "대부분, 주로",
  "slightly": "약간, 조금",
  "virtually": "거의, 사실상",
  "precisely": "정확하게, 신중하게",
  "evenly": "공평하게, 고르게",
  "tediously": "지루하게, 따분하게",
  "consistently": "지속적으로",
  "densely": "밀집하여, 빽빽하게",
  "initially": "초기에, 처음에",
  "loosely": "막연하게, 느슨하게",
  "generally": "일반적으로",
  "totally": "완전히, 모두",
  "reasonably": "적절히, 알맞게",
  "gently": "천천히, 부드럽게, 약하게",
  "nearly": "거의, 한 편이다",
  "regularly": "정기적으로, 자주",
  "exactly": "정확히, 바로, 틀림없이",
  "overly": "지나치게, 과도하게",
  "immeasurably": "잘 측을 수 없을 만큼",
  "successfully": "성공적으로",
  "regretfully": "유감스럽게도",
  "formerly": "이전에, 예전에",
  "rapidly": "급속히, 빠르게",
  "considerably": "훨씬, 상당히",
  "typically": "일반적으로, 전형적으로",
  "chiefly": "주로, 대개",
  "rightfully": "마땅히, 정당하게",
  "recently": "최근에",
  "entirely": "완전히, 전부",
  "continually": "계속적으로, 끊임없이",
  "once": "한 번",
  "first": "첫 번째로, 최초로",
  "be subject to": "~의 대상이다",
  "be similar to": "~과 비슷하다",
  "be pertinent to": "~과 관련 있다",
  "be unable to": "~할 수 없다",
  "be likely to": "~할 것 같다",
  "be popular with": "~에게 인기가 있다",
  "be familiar with": "~을 잘 알고 있다",
  "be eligible to": "~할 자격이 있다",
  "be intended for": "~을 대상으로 하다",
  "be dedicated to": "~에 전념하다",
  "be adequate for": "~에 적합하다, ~에 충분하다",
  "be equipped with": "~을 갖추고 있다",
  "be suitable for": "~에 알맞다, ~에 어울리다",
  "be skilled at": "~에 능숙하다, ~에 노련하다",
  "be willing to": "~할 용의가 있다",
  "be unaware of": "~에 대해 알지 못하다",
  "be bound to": "틀림없이 ~할 것이다",
  "be exempt from": "~이 면제되다",
  "be pleased to": "~하게 되어 기쁘다",
  "be selected for": "~에 뽑히다, ~에 선발되다",
  "acknowledge A for B": "A에게 B에 대해 감사하다",
  "associate A with B": "A를 B와 관련시켜 생각하다",
  "participate in": "~에 참가하다, ~에 참여하다",
  "designate A for B": "A를 B에 지정하다, 할당하다",
  "depend on": "~에 달려 있다",
  "result in": "~을 낳다, ~을 야기하다",
  "notify A of B": "A에게 B를 알리다",
  "come in": "(상품 등이 여러 종류로) 나오다",
  "recommend A for B": "A를 B에 추천하다",
  "proceed with": "~을 진행하다, ~을 처리하다",
  "provide A with B": "A에게 B를 제공하다",
  "prevent A from B": "A가 B하는 것을 막다, 예방하다",
  "preside over": "~을 주재하다, 사회를 보다",
  "ask A for B": "A에게 B를 요청하다",
  "specialize in": "~을 전문으로 하다",
  "substitute A for B": "A를 B로 대체하다",
  "lead to": "~으로 이어지다",
  "commend A for B": "A를 B에 대해 칭찬하다",
  "search for": "~을 찾아보다",
  "split up": "나누다, 분리되다",
  "attention to": "~에 대한 주의",
  "a portion of": "~의 일부, 약간의",
  "compliance with": "~의 준수, ~의 지킴",
  "identification badge": "신분 확인 명찰",
  "concerns about": "~에 대한 우려, 걱정",
  "intent to": "~할 의사, 의도, 목적",
  "effect on": "~에 대한 효과",
  "admiration for": "~에 대한 존경, 감탄",
  "shift in": "~의 변화",
  "restrictions on": "~에 대한 규제, 제한",
  "perspective on": "~에 대한 관점",
  "observation on": "~에 대한 논평, 의견",
  "commitment to": "~에 대한 헌신, 전념",
  "requirement for": "~을 위한 요건, 필요 조건",
  "transition from A to B": "A에서 B로의 변화, 이행",
  "investment in": "~에 대한 투자",
  "a source of": "~의 원천, 근원",
  "preparation for": "~을 위한 준비",
  "report for": "~를 위한 보고",
  "a consequence of": "~의 결과",
  "make arrangements": "준비하다",
  "open space": "공터",
  "work environment": "근무 환경",
  "concentrated effort": "집중적인 노력",
  "follow the regulations": "규정을 따르다",
  "selling point": "장점",
  "warm welcome": "따뜻한 환영",
  "thorough analysis": "철저한 분석",
  "eagerly await": "간절히 기다리다",
  "mutually beneficial": "상호적으로 이득이 되는",
  "strong performer": "경쟁력 있는 회사·사람",
  "take measures": "조치를 취하다",
  "quicken the pace": "속도를 높이다",
  "heavy usage": "과다 사용",
  "display initiative": "주도성을 발휘하다",
  "conveniently located": "편리하게 위치한",
  "steady growth": "꾸준한 성장",
  "cease operations": "영업을 중단하다",
  "sales performance": "판매 실적",
  "conduct an inspection": "점검을 실시하다",
  "promotion": "승진, 홍보",
  "personnel": "직원들, 인원",
  "subscriber": "구독자, 가입자",
  "retirement": "은퇴, 퇴직",
  "employment": "직장, 고용",
  "refund": "환불",
  "project": "프로젝트, 계획(기획)된 일",
  "construction": "건축, 공사",
  "outlook": "관점, 전망",
  "comparison": "비교",
  "relocation": "이전, 재배치",
  "career": "경력, 이력",
  "extent": "정도, 범위",
  "reception": "수령",
  "greeting": "인사, 환영",
  "separation": "분리",
  "occupation": "직업",
  "appliance": "가전기기",
  "volume": "양",
  "size": "크기",
  "estimate": "견적, 추정(액)",
  "reminder": "상기시켜 주는 메모, 독촉장",
  "procedure": "절차, 방법",
  "asset": "자산, 재산",
  "transaction": "거래, 처리",
  "enhancement": "향상, 증대",
  "challenge": "도전",
  "accomplishment": "성과, 업적",
  "objection": "반대",
  "convenience": "편의, 편리",
  "fee": "수수료, 요금",
  "publicity": "언론의 주목, 관심",
  "composition": "구성 (요소)",
  "development": "개발, 발달",
  "discretion": "재량(권), 신중함",
  "billing": "청구서 발송, 거래 총액",
  "retention": "(어떤 것을 잃지 않는) 유지, 보유",
  "candidate": "후보자, 지원자",
  "recognition": "인정",
  "permission": "허가, 승인",
  "performance": "공연, 수행",
  "issue": "(출판물의) 호, 발행물",
  "process": "절차, 과정",
  "transfer": "이동, 전근",
  "feasibility": "실행 가능성, 실현 가능성",
  "flavor": "맛, 풍미",
  "discrepancy": "불일치, 차이",
  "article": "기사",
  "celebration": "축하 행사",
  "priority": "우선순위",
  "handbook": "안내서",
  "transformation": "변화",
  "confirmation": "확인",
  "allowance": "수당",
  "competitor": "경쟁자",
  "instruction": "사용 설명서",
  "background": "(예비) 지식, 배경",
  "misconception": "오해",
  "barrier": "장벽, 장애물",
  "restraint": "규제",
  "maintenance": "정비, 보수 관리",
  "progress": "진행 상황, 진전",
  "resolution": "결심, 결정, 결단력",
  "specification": "세부 항목, 내역",
  "variation": "차이, 변형(시킨 것)",
  "authority": "당국, 권한",
  "disclosure": "공개",
  "coverage": "보도, 범위",
  "interruption": "중단, 방해",
  "factor": "요인, 요소",
  "premises": "구내, 토지",
  "collaboration": "협력, 공동 작업",
  "inquiry": "문의",
  "attendee": "참석자",
  "timeline": "시간표",
  "reversal": "전환, 역전",
  "complaint": "불평, 불만",
  "agenda": "안건, 의제",
  "replacement": "대체(품), 교체(품)",
  "renovation": "수리, 수선"
}